pyfreshintellivent/__init__.py
pyfreshintellivent/characteristics.py
pyfreshintellivent/consts.py
pyfreshintellivent/helpers.py
pyfreshintellivent/parser.py
pyfreshintellivent/scanner.py
pyfreshintellivent/sensors.py
pyfreshintellivent-0.3.4.dist-info/LICENSE
pyfreshintellivent-0.3.4.dist-info/LICENSE.md
pyfreshintellivent-0.3.4.dist-info/METADATA
pyfreshintellivent-0.3.4.dist-info/WHEEL
pyfreshintellivent-0.3.4.dist-info/RECORD
