Metadata-Version: 2.3
Name: pyfreshintellivent
Version: 0.3.4
Summary: Manage Fresh Intellivent Sky bathroom ventilation fan
License: Apache-2.0
Keywords: ble,ventilation,fresh,intellivent,sky
Author: Ståle Storø Hauknes
Author-email: walnut-caprice.04@icloud.com
Requires-Python: >=3.10,<3.14
Classifier: Development Status :: 3 - Alpha
Classifier: Intended Audience :: Developers
Classifier: License :: OSI Approved :: Apache Software License
Classifier: Programming Language :: Python :: 3.10
Classifier: Programming Language :: Python :: 3.11
Classifier: Programming Language :: Python :: 3.12
Classifier: Programming Language :: Python :: 3.13
Requires-Dist: bleak (>=1.0.0)
Requires-Dist: bleak-retry-connector (>=4.0.0,<5.0.0)
Project-URL: Repository, https://github.com/LaStrada/pyfreshintellivent
